civis/__init__.py
civis/_camel_to_snake.py
civis/_deprecation.py
civis/_get_api_key.py
civis/_retries.py
civis/base.py
civis/client.py
civis/client.pyi
civis/futures.py
civis/loggers.py
civis/parallel.py
civis/polling.py
civis/py.typed
civis/response.py
civis/run_joblib_func.py
civis/service_client.py
civis/cli/__init__.py
civis/cli/__main__.py
civis/cli/_cli_commands.py
civis/io/__init__.py
civis/io/_databases.py
civis/io/_files.py
civis/io/_tables.py
civis/io/_utils.py
civis/ml/__init__.py
civis/ml/_helper.py
civis/ml/_model.py
civis/resources/__init__.py
civis/resources/_api_spec.py
civis/resources/_client_pyi.py
civis/resources/_resources.py
civis/resources/civis_api_spec.json
civis/tests/__init__.py
civis/tests/mocks.py
civis/utils/__init__.py
civis/utils/_jobs.py
civis/workflows/__init__.py
civis/workflows/_schemas.py
civis/workflows/_validate.py
civis-2.8.0.dist-info/licenses/LICENSE.md
civis-2.8.0.dist-info/METADATA
civis-2.8.0.dist-info/WHEEL
civis-2.8.0.dist-info/entry_points.txt
civis-2.8.0.dist-info/top_level.txt
civis-2.8.0.dist-info/RECORD
