Metadata-Version: 2.4
Name: civis
Version: 2.8.0
Summary: Civis API Python Client
Author-email: Civis Analytics <opensource@civisanalytics.com>
License: BSD-3-Clause
Project-URL: Homepage, https://www.civisanalytics.com
Project-URL: Source, https://github.com/civisanalytics/civis-python
Classifier: Development Status :: 5 - Production/Stable
Classifier: License :: OSI Approved :: BSD License
Classifier: Programming Language :: Python
Classifier: Programming Language :: Python :: 3
Classifier: Programming Language :: Python :: 3 :: Only
Classifier: Programming Language :: Python :: 3.11
Classifier: Programming Language :: Python :: 3.12
Classifier: Programming Language :: Python :: 3.13
Classifier: Programming Language :: Python :: 3.14
Requires-Python: >=3.11
License-File: LICENSE.md
Requires-Dist: click>=6.0
Requires-Dist: cloudpickle>=0.2
Requires-Dist: joblib>=1.5.0
Requires-Dist: jsonref>=0.1
Requires-Dist: jsonschema>=2.5.1
Requires-Dist: PyYAML>=3.0
Requires-Dist: requests>=2.32.3
Requires-Dist: tenacity>=6.2
Requires-Dist: typing-extensions>=4.5.0; python_version < "3.13"
Provides-Extra: dev-core
Requires-Dist: bandit; extra == "dev-core"
Requires-Dist: black==25.12.0; extra == "dev-core"
Requires-Dist: build==1.3.0; extra == "dev-core"
Requires-Dist: flake8==7.3.0; extra == "dev-core"
Requires-Dist: mypy==1.19.1; extra == "dev-core"
Requires-Dist: pandas==2.3.3; extra == "dev-core"
Requires-Dist: pip-audit; extra == "dev-core"
Requires-Dist: polars==1.36.1; extra == "dev-core"
Requires-Dist: pytest==9.0.2; extra == "dev-core"
Requires-Dist: pytest-cov==7.0.0; extra == "dev-core"
Requires-Dist: twine==6.2.0; extra == "dev-core"
Requires-Dist: pandas-stubs; extra == "dev-core"
Requires-Dist: types-jsonschema; extra == "dev-core"
Requires-Dist: types-PyYAML; extra == "dev-core"
Requires-Dist: types-requests; extra == "dev-core"
Provides-Extra: dev-civisml
Requires-Dist: feather-format==0.4.1; extra == "dev-civisml"
Requires-Dist: numpy==2.4.0; extra == "dev-civisml"
Requires-Dist: scikit-learn==1.8.0; extra == "dev-civisml"
Requires-Dist: scipy==1.16.3; extra == "dev-civisml"
Provides-Extra: docs
Requires-Dist: numpydoc==1.8.0; extra == "docs"
Requires-Dist: Sphinx==8.2.3; extra == "docs"
Requires-Dist: sphinx-rtd-theme==3.0.2; extra == "docs"
Dynamic: license-file
